aminofixed
