Metadata-Version: 2.1
Name: Amino.fixed
Version: 1.0.1
Summary: An API about lib Fix Amino.py
Author: Codex and Arjun
Keywords: python,bot,aminobot,theamino
Classifier: Development Status :: 1 - Planning
Classifier: Intended Audience :: Developers
Classifier: Programming Language :: Python :: 3
Classifier: Operating System :: Unix
Classifier: Operating System :: MacOS :: MacOS X
Classifier: Operating System :: Microsoft :: Windows
Requires-Python: >=3.10
License-File: LICENSE.txt
